LICENSE.txt
MANIFEST.in
README.rst
pyproject.toml
setup.py
example/open_write_read_close.py
example/probe.py
libs/liburing/LICENSE
libs/liburing/Makefile
libs/liburing/Makefile.common
libs/liburing/Makefile.quiet
libs/liburing/configure
libs/liburing/liburing-ffi.pc.in
libs/liburing/liburing.pc.in
libs/liburing/liburing.spec
libs/liburing/src/Makefile
libs/liburing/src/ffi.c
libs/liburing/src/int_flags.h
libs/liburing/src/lib.h
libs/liburing/src/liburing-ffi.map
libs/liburing/src/liburing.map
libs/liburing/src/nolibc.c
libs/liburing/src/queue.c
libs/liburing/src/register.c
libs/liburing/src/setup.c
libs/liburing/src/setup.h
libs/liburing/src/syscall.c
libs/liburing/src/syscall.h
libs/liburing/src/version.c
libs/liburing/src/arch/syscall-defs.h
libs/liburing/src/arch/aarch64/lib.h
libs/liburing/src/arch/aarch64/syscall.h
libs/liburing/src/arch/generic/lib.h
libs/liburing/src/arch/generic/syscall.h
libs/liburing/src/arch/riscv64/lib.h
libs/liburing/src/arch/riscv64/syscall.h
libs/liburing/src/arch/x86/lib.h
libs/liburing/src/arch/x86/syscall.h
libs/liburing/src/include/liburing.h
libs/liburing/src/include/liburing/barrier.h
libs/liburing/src/include/liburing/io_uring.h
src/liburing/__init__.pxd
src/liburing/__init__.py
src/liburing/_test.pxd
src/liburing/_test.pyx
src/liburing/common.pxd
src/liburing/common.pyx
src/liburing/error.pxd
src/liburing/error.pyx
src/liburing/file.pxd
src/liburing/file.pyx
src/liburing/futex.pxd
src/liburing/futex.pyx
src/liburing/helper.pxd
src/liburing/helper.pyx
src/liburing/os.pxd
src/liburing/os.pyx
src/liburing/other.pxd
src/liburing/other.pyx
src/liburing/poll.pxd
src/liburing/poll.pyx
src/liburing/probe.pxd
src/liburing/probe.py
src/liburing/probe.pyx
src/liburing/queue.pxd
src/liburing/queue.pyx
src/liburing/register.pxd
src/liburing/register.pyx
src/liburing/socket.pxd
src/liburing/socket.pyx
src/liburing/socket_extra.pxd
src/liburing/socket_extra.pyx
src/liburing/statx.pxd
src/liburing/statx.pyx
src/liburing/syscall.pxd
src/liburing.egg-info/PKG-INFO
src/liburing.egg-info/SOURCES.txt
src/liburing.egg-info/dependency_links.txt
src/liburing.egg-info/requires.txt
src/liburing.egg-info/top_level.txt
