Metadata-Version: 2.1
Name: liburing
Version: 2024.4.22
Summary: ...
Author: Ritesh
License: Creative Commons Legal Code
Project-URL: Homepage, https://github.com/YoSTEALTH/Liburing
Project-URL: Issues, https://github.com/YoSTEALTH/Liburing/issues
Classifier: Topic :: Software Development
Classifier: License :: Public Domain
Classifier: Intended Audience :: Developers
Classifier: Operating System :: POSIX :: Linux
Classifier: Programming Language :: Python :: 3.8
Classifier: Programming Language :: Python :: 3.9
Classifier: Programming Language :: Python :: 3.10
Classifier: Programming Language :: Python :: 3.11
Classifier: Programming Language :: Python :: 3.12
Classifier: Development Status :: 3 - Alpha
Requires-Python: >=3.8
License-File: LICENSE.txt
Requires-Dist: dynamic-import
Provides-Extra: test
Requires-Dist: pytest; extra == "test"
